[
	{
		"id": "latte",
		"price": 4.50,
		"serving_size": "12oz"
	},
	{
		"id": "vanilla_latte",
		"price": 4.75,
		"serving_size": "12oz"
	},
	{
		"id": "chocolate_mocha",
		"price": 4.75,
		"serving_size": "12oz"
	},
	{
		"id": "caramel_macchiato",
		"price": 4.75,
		"serving_size": "12oz"
	},
	{
		"id": "white_chocolate_mocha",
		"price": 4.75,
		"serving_size": "12oz"
	},
	{
		"id": "cappuccino",
		"price": 4.75,
		"serving_size": "6oz"
	},
	{
		"id": "latte",
		"price": 5.25,
		"serving_size": "16oz"
	},
	{
		"id": "vanilla_latte",
		"price": 5.5,
		"serving_size": "16oz"
	},
	{
		"id": "chocolate_mocha",
		"price": 5.5,
		"serving_size": "16oz"
	},
	{
		"id": "caramel_macchiato",
		"price": 5.5,
		"serving_size": "16oz"
	},
	{
		"id": "white_chocolate_mocha",
		"price": 5.5,
		"serving_size": "16oz"
	}
]
